README.md
setup.cfg
setup.py
onshape_client/__init__.py
onshape_client/oas/__init__.py
onshape_client/oas/api_client.py
onshape_client/oas/configuration.py
onshape_client/oas/exceptions.py
onshape_client/oas/model_utils.py
onshape_client/oas/rest.py
onshape_client/oas/api/__init__.py
onshape_client/oas/api/account_api.py
onshape_client/oas/api/alias_api.py
onshape_client/oas/api/api_application_api.py
onshape_client/oas/api/app_associative_data_api.py
onshape_client/oas/api/app_element_api.py
onshape_client/oas/api/assembly_api.py
onshape_client/oas/api/billing_api.py
onshape_client/oas/api/blob_element_api.py
onshape_client/oas/api/classroom_api.py
onshape_client/oas/api/comment_api.py
onshape_client/oas/api/company_api.py
onshape_client/oas/api/document_api.py
onshape_client/oas/api/drawing_api.py
onshape_client/oas/api/element_api.py
onshape_client/oas/api/export_rule_api.py
onshape_client/oas/api/feature_studio_api.py
onshape_client/oas/api/folder_api.py
onshape_client/oas/api/insertable_api.py
onshape_client/oas/api/metadata_api.py
onshape_client/oas/api/metadata_category_api.py
onshape_client/oas/api/open_api_api.py
onshape_client/oas/api/part_api.py
onshape_client/oas/api/part_number_api.py
onshape_client/oas/api/part_studio_api.py
onshape_client/oas/api/publication_api.py
onshape_client/oas/api/release_package_api.py
onshape_client/oas/api/revision_api.py
onshape_client/oas/api/sketch_api.py
onshape_client/oas/api/team_api.py
onshape_client/oas/api/thumbnail_api.py
onshape_client/oas/api/translation_api.py
onshape_client/oas/api/user_api.py
onshape_client/oas/api/version_api.py
onshape_client/oas/api/webhook_api.py
onshape_client/oas/api/workflow_api.py
onshape_client/oas/api/workflowable_test_object_api.py
onshape_client/oas/apis/__init__.py
onshape_client/oas/model/__init__.py
onshape_client/oas/model/address.py
onshape_client/oas/model/bt_acl_entry_info.py
onshape_client/oas/model/bt_acl_info.py
onshape_test_client.egg-info/PKG-INFO
onshape_test_client.egg-info/SOURCES.txt
onshape_test_client.egg-info/dependency_links.txt
onshape_test_client.egg-info/requires.txt
onshape_test_client.egg-info/top_level.txt
