Metadata-Version: 1.2
Name: onshape-test-client
Version: 1.0.0
Summary: Onshape REST API
Home-page: UNKNOWN
Author: OpenAPI Generator community
Author-email: api-support@onshape.zendesk.com
License: Apache 2.0
Keywords: OpenAPI,OpenAPI-Generator,Onshape REST API
Platform: UNKNOWN
Requires-Python: >=3.9
